resolver/__init__.py
resolver/_base.py
resolver/_functions.py
resolver/_version.py
resolver/entlet.py
resolver/entletmap.py
resolver/filter.py
resolver/pipeline.py
resolver/strategy.py
entity_resolution-0.1.0.dist-info/LICENSE
entity_resolution-0.1.0.dist-info/METADATA
entity_resolution-0.1.0.dist-info/WHEEL
entity_resolution-0.1.0.dist-info/top_level.txt
entity_resolution-0.1.0.dist-info/RECORD
