Metadata-Version: 2.1
Name: entity-resolution
Version: 0.1.0
Summary: Extensible entity resolution framework
Home-page: 
Author: Carl Best
Author-email: 
License: UNKNOWN
Platform: UNKNOWN
Classifier: Programming Language :: Python :: 3
Classifier: Operating System :: OS Independent
Requires-Python: >=3.6
License-File: LICENSE
Requires-Dist: Levenshtein (<0.19,>=0.18.0)
Requires-Dist: networkx (<3.0,>=2.7)
Requires-Dist: numpy (<2.0,>=1.22)
Requires-Dist: pandas (<2.0,>=1.3.0)
Requires-Dist: scikit-learn (>=1.0.0)
Requires-Dist: scipy (<2.0,>=1.8)
